nwebsocket/__init__.py
nwebsocket/events.py
nwebsocket/utils.py
nwebsocket-1.0.0.dist-info/LICENSE
nwebsocket-1.0.0.dist-info/METADATA
nwebsocket-1.0.0.dist-info/WHEEL
nwebsocket-1.0.0.dist-info/top_level.txt
nwebsocket-1.0.0.dist-info/RECORD
